chATLAS_Scrape/__init__.py
chATLAS_Scrape/gitlab/__init__.py
chATLAS_Scrape/gitlab/config.py
chATLAS_Scrape/gitlab/get_markdown.py
chATLAS_Scrape/gitlab/get_projects.py
chATLAS_Scrape/gitlab/rate_limiter.py
chatlas_scrape-0.0.1.dist-info/licenses/LICENSE
tests/gitlab/test_gitlab.py
chatlas_scrape-0.0.1.dist-info/METADATA
chatlas_scrape-0.0.1.dist-info/WHEEL
chatlas_scrape-0.0.1.dist-info/top_level.txt
chatlas_scrape-0.0.1.dist-info/RECORD
