Metadata-Version: 2.4
Name: chATLAS_Scrape
Version: 0.0.1
Summary: A python package for scraping input data for chATLAS.
Author: chATLAS Team
License: Apache-2.0
Classifier: Programming Language :: Python :: 3
Classifier: License :: OSI Approved :: Apache Software License
Classifier: Operating System :: OS Independent
Requires-Python: >=3.11
License-File: LICENSE
Requires-Dist: requests>=2.32.3
Requires-Dist: pandas>=2.0.0
Dynamic: license-file
